aws_ses_service/__init__.py
aws_ses_service/attachment.py
aws_ses_service/body.py
aws_ses_service-0.0.12.dist-info/LICENSE
aws_ses_service-0.0.12.dist-info/METADATA
aws_ses_service-0.0.12.dist-info/WHEEL
aws_ses_service-0.0.12.dist-info/top_level.txt
aws_ses_service-0.0.12.dist-info/RECORD
