Metadata-Version: 2.1
Name: aws-ses-service
Version: 0.0.12
Summary: This library is to help send emails using AWS ses service
Home-page: https://github.com/Quakingaspen-codehub/aws_ses_service
Author: Quaking Aspen
Author-email: info@quakingaspen.net
License: UNKNOWN
Platform: UNKNOWN
Classifier: Programming Language :: Python :: 3
Classifier: License :: OSI Approved :: MIT License
Classifier: Operating System :: OS Independent
Requires-Python: >=3.6
Requires-Dist: aws-s3-resource
Requires-Dist: boto3
